python_gist_note/__init__.py
python_gist_note/gn.py
python_gist_note-0.2.4.data/scripts/gn
python_gist_note-0.2.4.dist-info/DESCRIPTION.rst
python_gist_note-0.2.4.dist-info/METADATA
python_gist_note-0.2.4.dist-info/RECORD
python_gist_note-0.2.4.dist-info/WHEEL
python_gist_note-0.2.4.dist-info/metadata.json
python_gist_note-0.2.4.dist-info/top_level.txt
