Metadata-Version: 2.0
Name: python-gist-note
Version: 0.2.4
Summary: just a simple code sharing tool powered by gist.
Home-page: https://github.com/tonghuashuai/python-gist-note
Author: tonghs
Author-email: tonghuashuai@gmail.com
License: MIT License
Keywords: note,gist,gist-note,gn,code share
Platform: any
Requires-Dist: requests
